Metadata-Version: 2.1
Name: odoo14-addon-contract_queue_job
Version: 14.0.1.0.1.dev9
Summary: This addon make contract invoicing cron plan each contract in a job instead of creating all invoices in one transaction
Home-page: https://github.com/OCA/contract
Author: ACSONE SA/NV,Odoo Community Association (OCA)
Author-email: support@odoo-community.org
License: AGPL-3
Classifier: Programming Language :: Python
Classifier: Framework :: Odoo
Classifier: Framework :: Odoo :: 14.0
Classifier: License :: OSI Approved :: GNU Affero General Public License v3
Requires-Python: >=3.6
Requires-Dist: odoo14-addon-contract
Requires-Dist: odoo14-addon-queue-job
Requires-Dist: odoo<14.1dev,>=14.0a
